cookie_policy/__init__.py
cookie_policy/admin.py
cookie_policy/apps.py
cookie_policy/info.py
cookie_policy/models.py
cookie_policy/tests.py
cookie_policy/urls.py
cookie_policy/views.py
cookie_policy/locale/en/LC_MESSAGES/django.po
cookie_policy/locale/ja/LC_MESSAGES/django.po
cookie_policy/locale/zh_hans/LC_MESSAGES/django.po
cookie_policy/locale/zh_hant/LC_MESSAGES/django.po
cookie_policy/migrations/0001_initial.py
cookie_policy/migrations/__init__.py
cookie_policy/static/cookie_agreement/cookie.css
cookie_policy/static/cookie_agreement/cookie.js
cookie_policy/templates/cookie_agreement.html
cookie_policy/templatetags/__init__.py
cookie_policy/templatetags/cookie_agreement.py
ponddy_cookie_agreement-0.0.9.dist-info/METADATA
ponddy_cookie_agreement-0.0.9.dist-info/WHEEL
ponddy_cookie_agreement-0.0.9.dist-info/top_level.txt
ponddy_cookie_agreement-0.0.9.dist-info/RECORD
