Metadata-Version: 2.1
Name: ponddy-cookie-agreement
Version: 0.0.9
Summary: The cookie agreement API for logging user agreement
Home-page: https://github.com/samwuTW/ponddy-cookie-agreement
Author: lambdaTW
Author-email: lambda@lambda.tw
License: MIT
Keywords: Ponddy cookie GDPR
Platform: UNKNOWN
Classifier: Programming Language :: Python :: 3.7
Classifier: Programming Language :: Python :: 3.6
Requires-Dist: Django
Requires-Dist: djangorestframework
